README.md
setup.py
imdbdump/imdb_fetcher.py
imdbdump.egg-info/PKG-INFO
imdbdump.egg-info/SOURCES.txt
imdbdump.egg-info/dependency_links.txt
imdbdump.egg-info/not-zip-safe
imdbdump.egg-info/requires.txt
imdbdump.egg-info/top_level.txt