Metadata-Version: 2.1
Name: imdbdump
Version: 0.1.2
Summary: Helps you to dump TV show IMDb ratings in machine-readable formats.
Home-page: http://github.com/fuuman/imdbdump
Author: Marco Schanz
Author-email: mschanz1210@gmail.com
License: GNU GPLv3
Platform: UNKNOWN
